[
    {
        "name": "kadın",
        "steps": [
            {
                "step": 0,
                "type": "question",
                "subtype": "category",
                "title": "Hangi kategoride ürün arıyorsunuz?",
                "answers": ["kadın", "erkek", "outlet", "çocuk"]
            },
            {
                "step": 1,
                "type": "color",
                "subtype": "color",
                "title": "Hangi renk?",
                "answers": ["siyah", "bej", "beyaz", "mavi", "kırmızı", "yeşil"]
            },
            {
                "step": 2,
                "type": "price",
                "subtype": "price",
                "title": "Fiyat aralığı seçiniz",
                "subtitle": "Lets think about the money...",
                "answers": ["0-1000", "1000-2000", "2000+"]
            }
        ]
    },
    {
        "name": "erkek",
        "steps": [
            {
                "step": 0,
                "type": "question",
                "subtype": "category",
                "title": "Hangi kategoride ürün arıyorsunuz?",
                "answers": ["kadın", "erkek", "outlet", "çocuk"]
            },
            {
                "step": 1,
                "type": "color",
                "subtype": "color",
                "title": "Hangi renk?",
                "answers": ["siyah", "bej", "beyaz", "mavi", "kırmızı", "yeşil"]
            },
            {
                "step": 2,
                "type": "price",
                "subtype": "price",
                "title": "Fiyat aralığı seçiniz",
                "answers": ["0-1000", "1000-2000", "2000+"]
            }
        ]
    },
    {
        "name": "çocuk",
        "steps": [
            {
                "step": 0,
                "type": "question",
                "subtype": "category",
                "title": "Hangi kategoride ürün arıyorsunuz?",
                "answers": ["kadın", "erkek", "outlet", "çocuk"]
            },
            {
                "step": 0,
                "type": "color",
                "subtype": "color",
                "title": "Hangi renk?",
                "answers": ["siyah", "bej", "beyaz", "mavi", "kırmızı", "yeşil"]
            },
            {
                "step": 1,
                "type": "price",
                "subtype": "price",
                "title": "Fiyat aralığı seçiniz",
                "answers": ["0-1000", "1000-2000", "2000+"]
            }
        ]
    },
    {
      "name": "outlet",
      "steps": [
          {
              "step": 0,
              "type": "question",
              "subtype": "category",
              "title": "Hangi kategoride ürün arıyorsunuz?",
              "answers": ["kadın", "erkek", "outlet", "çocuk"]
          },
          {
              "step": 0,
              "type": "color",
              "subtype": "color",
              "title": "Hangi renk?",
              "answers": ["siyah", "bej", "beyaz", "mavi", "kırmızı", "yeşil"]
          },
          {
              "step": 1,
              "type": "price",
              "subtype": "price",
              "title": "Fiyat aralığı seçiniz",
              "answers": ["0-1000", "1000-2000", "2000+"]
          }
      ]
  }
  ]